datatransport/__init__.py
datatransport/accessmixin.py
datatransport/configcomponent.py
datatransport/directory.py
datatransport/metadata.py
datatransport/newspoller.py
datatransport/newsposter.py
datatransport/newstool.py
datatransport/processclient.py
datatransport/processgroup.py
datatransport/root.py
datatransport/transportconfig.py
datatransport/transportlogger.py
datatransport/transportmanager.py
datatransport/transportserver.py
datatransport/xmlrpcserver.py
datatransport/apps/EventMonitor.py
datatransport/apps/InstrumentStatus.py
datatransport/apps/NewsgroupMonitor.py
datatransport/apps/PageKit.py
datatransport/apps/PlotTool.py
datatransport/apps/__init__.py
datatransport/apps/archivegroups.py
datatransport/apps/directoryservice.py
datatransport/apps/diskmonitor.py
datatransport/apps/filepost.py
datatransport/apps/filewatch.py
datatransport/apps/groupcontrol.py
datatransport/apps/newsgateway.py
datatransport/apps/postdatafiles.py
datatransport/apps/realtimefeed.py
datatransport/apps/resourcemonitor.py
datatransport/apps/scheduler.py
datatransport/apps/syncpoller.py
datatransport/apps/watchurl.py
datatransport/commands/__init__.py
datatransport/commands/cancelnewsgroup.py
datatransport/commands/console.py
datatransport/commands/createnewsgroup.py
datatransport/commands/listnewsgroups.py
datatransport/commands/rmnewsgroup.py
datatransport/commands/transport_create_app.py
datatransport/commands/transport_get_article.py
datatransport/commands/transport_post_article.py
datatransport/commands/transportctl.py
datatransport/commands/transportd.py
datatransport/commands/transportps.py
datatransport/commands/viewlog.py
datatransport/templates/etc/transportd.conf
datatransport/templates/groups/ServerMonitor/ServerMonitor.conf
datatransport/templates/groups/ServerMonitor/watchdog.py
datatransport/utilities/__init__.py
datatransport/utilities/datefunc.py
datatransport/utilities/makepath.py
datatransport/utilities/patterntemplate.py
datatransport/utilities/removefile.py
datatransport-3.0.24.dist-info/METADATA
datatransport-3.0.24.dist-info/WHEEL
datatransport-3.0.24.dist-info/entry_points.txt
datatransport-3.0.24.dist-info/licenses/LICENSE
datatransport-3.0.24.dist-info/RECORD
