Metadata-Version: 2.4
Name: datatransport
Version: 3.0.24
Summary: Data Transport Network
Project-URL: homepage, https://github.com/valentic/datatransport
Project-URL: repository, https://github.com/valentic/datatransport
Author-email: Todd Valentic <todd.valentic@gmail.com>
License:                     GNU GENERAL PUBLIC LICENSE
License-File: LICENSE
Classifier: License :: OSI Approved :: GNU General Public License v3 (GPLv3)
Classifier: Operating System :: OS Independent
Classifier: Programming Language :: Python :: 3
Requires-Python: >=3.9
Requires-Dist: importlib-resources>1.3; python_version < '3.10'
Requires-Dist: python-dateutil
Requires-Dist: pytimeparse2
Requires-Dist: sapphire-config
Requires-Dist: standard-asyncore; python_version >= '3.12'
Requires-Dist: standard-nntplib; python_version >= '3.12'
Requires-Dist: texttable
Provides-Extra: devel
Requires-Dist: pyfakefs; extra == 'devel'
Requires-Dist: pytest; extra == 'devel'
Requires-Dist: ruff; extra == 'devel'
